blosc_reader/__init__.py
blosc_reader/blosc_reader.py
blosc_reader-0.1.0.dist-info/LICENSE
blosc_reader-0.1.0.dist-info/METADATA
blosc_reader-0.1.0.dist-info/WHEEL
blosc_reader-0.1.0.dist-info/entry_points.txt
blosc_reader-0.1.0.dist-info/top_level.txt
blosc_reader-0.1.0.dist-info/RECORD
